{
  "schema_version": "9A.4.v1",
  "run_scope_id": "run_9b_lumaloop_ea818fbeeb21",
  "discussion_session_id": "ba058dd9-311d-469d-a131-e42b545024c9",
  "product_name": "LumaLoop",
  "launch_state": "unlaunched",
  "generated_at": "2026-05-08T05:16:17.388296+00:00",
  "header_caveat": "_This is a synthetic discussion simulation. n=30 persisted society, 5 groups of 6 personas. Not representative of the California market. Not a forecast. Not a demand forecast. Not a launch verdict. The product is unlaunched \u2014 no persona has actually used it._",
  "executive_summary": [
    "This is a synthetic discussion simulation across 66 run-scoped personas in 5 groups of 6.",
    "Pre-discussion private stance distribution: {'interested_if_proven': 31, 'skeptical': 7, 'needs_more_information': 21, 'curious_but_unconvinced': 7}.",
    "Post-discussion private stance distribution: {'interested_if_proven': 54, 'skeptical': 4, 'curious_but_unconvinced': 7, 'needs_more_information': 1}.",
    "Social-influence classification: {'resistance': 15, 'no_change': 51}.",
    "No over-cooperation detected. Public/private distinction preserved.",
    "Discussion quality aggregate: 0.976 (READY_FOR_PROMPT_FIX)."
  ],
  "discussion_setup": {
    "persona_count": 66,
    "group_count": 11,
    "group_size": 6,
    "structure": "0 pre-ballot \u00b7 1 public opening \u00b7 2 challenge \u00b7 3 peer-response \u00b7 4 proof discussion \u00b7 5 reflection \u00b7 6 final ballot"
  },
  "group_composition": [
    {
      "group_index": 0,
      "personas": [
        "Riley C.",
        "Avery A.",
        "Casey P.",
        "Gray T.",
        "Jordan N.",
        "Nico K."
      ],
      "metadata": {
        "personas": [
          "Riley C.",
          "Avery A.",
          "Casey P.",
          "Gray T.",
          "Jordan N.",
          "Nico K."
        ]
      }
    },
    {
      "group_index": 1,
      "personas": [
        "Tatum W.",
        "Sage D.",
        "Logan J.",
        "Maya C.",
        "Sage C.",
        "Maya A."
      ],
      "metadata": {
        "personas": [
          "Tatum W.",
          "Sage D.",
          "Logan J.",
          "Maya C.",
          "Sage C.",
          "Maya A."
        ]
      }
    },
    {
      "group_index": 2,
      "personas": [
        "Jules J.",
        "Logan C.",
        "Kerry K.",
        "Jules M.",
        "Ellis G.",
        "Marlowe B."
      ],
      "metadata": {
        "personas": [
          "Jules J.",
          "Logan C.",
          "Kerry K.",
          "Jules M.",
          "Ellis G.",
          "Marlowe B."
        ]
      }
    },
    {
      "group_index": 3,
      "personas": [
        "Wren A.",
        "Blair D.",
        "Winslow F.",
        "Logan R.",
        "Morgan A.",
        "Lennon J."
      ],
      "metadata": {
        "personas": [
          "Wren A.",
          "Blair D.",
          "Winslow F.",
          "Logan R.",
          "Morgan A.",
          "Lennon J."
        ]
      }
    },
    {
      "group_index": 4,
      "personas": [
        "Umber M.",
        "Vesper F.",
        "Drew L.",
        "Drew W.",
        "Vesper G.",
        "Ellis L."
      ],
      "metadata": {
        "personas": [
          "Umber M.",
          "Vesper F.",
          "Drew L.",
          "Drew W.",
          "Vesper G.",
          "Ellis L."
        ]
      }
    },
    {
      "group_index": 5,
      "personas": [
        "Quinn T.",
        "Marlowe F.",
        "Quinn L.",
        "Oakley W.",
        "Jules R.",
        "Maya B."
      ],
      "metadata": {
        "personas": [
          "Quinn T.",
          "Marlowe F.",
          "Quinn L.",
          "Oakley W.",
          "Jules R.",
          "Maya B."
        ]
      }
    },
    {
      "group_index": 6,
      "personas": [
        "Nico W.",
        "Sage G.",
        "Skyler N.",
        "Nico W.",
        "Casey K.",
        "Morgan F."
      ],
      "metadata": {
        "personas": [
          "Nico W.",
          "Sage G.",
          "Skyler N.",
          "Nico W.",
          "Casey K.",
          "Morgan F."
        ]
      }
    },
    {
      "group_index": 7,
      "personas": [
        "Riley F.",
        "Morgan T.",
        "Lennon L.",
        "Drew J.",
        "Sage W.",
        "Skyler T."
      ],
      "metadata": {
        "personas": [
          "Riley F.",
          "Morgan T.",
          "Lennon L.",
          "Drew J.",
          "Sage W.",
          "Skyler T."
        ]
      }
    },
    {
      "group_index": 8,
      "personas": [
        "Skyler P.",
        "Skyler S.",
        "Xael L.",
        "Jordan C.",
        "Quinn V.",
        "Xael B."
      ],
      "metadata": {
        "personas": [
          "Skyler P.",
          "Skyler S.",
          "Xael L.",
          "Jordan C.",
          "Quinn V.",
          "Xael B."
        ]
      }
    },
    {
      "group_index": 9,
      "personas": [
        "Casey C.",
        "Gray P.",
        "Gray P.",
        "Nico W.",
        "Skyler K.",
        "Yarrow M."
      ],
      "metadata": {
        "personas": [
          "Casey C.",
          "Gray P.",
          "Gray P.",
          "Nico W.",
          "Skyler K.",
          "Yarrow M."
        ]
      }
    },
    {
      "group_index": 10,
      "personas": [
        "Xael K.",
        "Riley V.",
        "Phoenix K.",
        "Reese M.",
        "Yarrow R.",
        "Finley C."
      ],
      "metadata": {
        "personas": [
          "Xael K.",
          "Riley V.",
          "Phoenix K.",
          "Reese M.",
          "Yarrow R.",
          "Finley C."
        ]
      }
    }
  ],
  "public_opening_stances": [
    {
      "speaker": "Jules J.",
      "stance": "needs_more_information",
      "text": "I run most evenings, so anything pitched as a wearable light catches my eye \u2014 but I haven't seen LumaLoop in person, just the name. Before I'd put it next to my Noxgear vest or a basic Nathan strap, I'd want specifics: lumens, runtime, how it handles sweat and rain, and whether t"
    },
    {
      "speaker": "Logan C.",
      "stance": "needs_more_information",
      "text": "Format-wise, what I want to know up front: how many LEDs, what's the fiber optic diameter, and does it do dual-color modes? That's the bar Noxgear set with the Tracer2 \u2014 4 LEDs, fatter fiber, dual-color. If LumaLoop can't spec out cleanly against that, I don't see the format stor"
    },
    {
      "speaker": "Kerry K.",
      "stance": "needs_more_information",
      "text": "Honestly, I haven't seen enough on LumaLoop to form an opinion yet. Before I'd consider it over something like a Flare RT, I'd want to see real specs \u2014 lumens, run time, mounting, weather sealing \u2014 and ideally some independent daytime visibility testing. Brand claims alone don't "
    },
    {
      "speaker": "Jules M.",
      "stance": "needs_more_information",
      "text": "Coming at this from a convenience angle \u2014 for my 1-2 hour runs I lean toward lighter, battery-driven setups like the Black Diamond Sprinter rather than something I have to fuss over. I don't know enough about LumaLoop's weight, charge time, or beam pattern to say where it lands a"
    },
    {
      "speaker": "Ellis G.",
      "stance": "needs_more_information",
      "text": "Coming from years of running with Amphipod waist packs and handhelds, my bar for any new gear is pretty specific: does it stay put on long endurance efforts, can I customize the load, and is there real proof \u2014 not marketing copy \u2014 that it holds up? I haven't seen spec sheets or i"
    },
    {
      "speaker": "Marlowe B.",
      "stance": "interested_if_proven",
      "text": "Coming at this from a running/trail-use angle, what I want to know about LumaLoop is real lumen output, beam pattern, and how the weight sits during hard efforts \u2014 that's the bar something like a Black Diamond Sprinter sets. Branding and form factor don't mean much to me without "
    },
    {
      "speaker": "Riley C.",
      "stance": "needs_more_information",
      "text": "Honestly, I haven't seen enough on LumaLoop to know if it actually saves me time or just adds another thing to fuss with. What I care about is whether setup is quick, it works without babysitting, and the price isn't wild compared to what's already out there. If someone has concr"
    },
    {
      "speaker": "Avery A.",
      "stance": "needs_more_information",
      "text": "Before I'd put LumaLoop on my shortlist, I need hard specs \u2014 lumen output, reflective area in square inches, battery runtime, weather sealing, and ideally an EN 17353 or ANSI 107 reference. My Nathan reflective vest runs $40 and the Reflex slap bands are cheap insurance, so whate"
    },
    {
      "speaker": "Casey P.",
      "stance": "skeptical",
      "text": "Honestly, my first question on LumaLoop is what's it going to cost me versus just clipping a $15 reflective vest and a cheap LED band on. I've seen plenty of 'visibility gear' that looks like a walking Christmas tree and runs three figures \u2014 and I'm not sold the upgrade is worth "
    },
    {
      "speaker": "Gray T.",
      "stance": "needs_more_information",
      "text": "I've been running with the Black Diamond Sprinter for a while, so I'm coming at LumaLoop from that lens \u2014 solid rear strap counterweight, decent beam, and I know exactly what I'm getting at that price point. Without specs in hand I can't really say where LumaLoop lands on weight,"
    },
    {
      "speaker": "Jordan N.",
      "stance": "needs_more_information",
      "text": "Honestly, before I can have an opinion on LumaLoop I need to know what format we're actually talking about \u2014 is it a wearable, an accessory, a pack add-on? When I look at gear like MTB cargo shorts, the whole pitch lives or dies on pocket layout, materials, and how it carries on "
    },
    {
      "speaker": "Nico K.",
      "stance": "needs_more_information",
      "text": "My main use case is visibility on early morning and evening walks with my dog \u2014 I want drivers and cyclists to actually see us. I've tried reflective collars and a couple of clip-on LED lights, so before I'd consider LumaLoop I'd want to know how it compares on brightness, batter"
    },
    {
      "speaker": "Casey C.",
      "stance": "needs_more_information",
      "text": "Haven't seen LumaLoop in person, so I'm reserving judgment, but for night runs I've been leaning on my Nathan QuickStart vest with reflective detailing and a clip light \u2014 that combo is hard to beat for longer outings. Curious what LumaLoop actually does differently: is it passive"
    },
    {
      "speaker": "Gray P.",
      "stance": "needs_more_information",
      "text": "Honestly, what I want to know about LumaLoop is how easy it is to just throw on and go. I've seen those clip-on shoe lights that slip over laces \u2014 no fuss, no straps, you forget they're there \u2014 so whatever this is, it needs to clear that bar for me. If it takes more than a few se"
    },
    {
      "speaker": "Gray P.",
      "stance": "interested_if_proven",
      "text": "For me a running light lives or dies on burn time at the brightness I actually run at, beam pattern, and how it handles rain and bounce. I haven't seen LumaLoop's specs in detail \u2014 lumens sustained vs peak, runtime curve, weight, mount stability \u2014 so I can't really place it again"
    },
    {
      "speaker": "Nico W.",
      "stance": "curious_but_unconvinced",
      "text": "Look, I run with a Tracer 2 and for under a hundred bucks I get 360-degree LED visibility plus reflective patterns \u2014 that's a hard bar to clear. I haven't tried LumaLoop, so I'm not writing it off, but I want to see specs side-by-side: lumens, battery life, weight, and most impor"
    },
    {
      "speaker": "Skyler K.",
      "stance": "interested_if_proven",
      "text": "Honestly, before I'd even consider LumaLoop, I'd want to see hard proof \u2014 independent visibility tests, certifications, actual side-by-side comparisons against the established reflective vests and clip lights people already trust. I've read enough reviews of 'sought-after' visibi"
    },
    {
      "speaker": "Yarrow M.",
      "stance": "needs_more_information",
      "text": "As a night runner, I'm always on the lookout for visibility gear that actually works on the move \u2014 shoe lights, clip-ons, reflective vests, that kind of thing. LumaLoop sounds like it could fit that niche, but I'd want to know specifics: how it attaches, battery life, weight, wat"
    },
    {
      "speaker": "Tatum W.",
      "stance": "needs_more_information",
      "text": "Haven't tried the LumaLoop, so I'm coming in cold. My Black Diamond Sprinter has been solid for years \u2014 rechargeable, rear red light, decent beam \u2014 so anything new has to clearly beat that on weight, runtime, or comfort before I'd even think about switching. Curious what the actu"
    },
    {
      "speaker": "Sage D.",
      "stance": "curious_but_unconvinced",
      "text": "I've been running with the Noxgear Tracer2 for a while, and the bounce-free fiber optic harness sets a pretty high bar for me \u2014 it genuinely disappears when you're moving. I'd want to know how LumaLoop handles weight distribution, whether it stays put on technical trail descents,"
    },
    {
      "speaker": "Logan J.",
      "stance": "interested_if_proven",
      "text": "Honest take: I haven't tried LumaLoop, and before I'd consider it I'd want to see the same kind of proof I lean on for gear like Nathan's reflective stuff \u2014 a real review count with averages, not just brand copy. How does it actually compare to established reflective bands or cli"
    },
    {
      "speaker": "Maya C.",
      "stance": "needs_more_information",
      "text": "Coming at this from the Amphipod Xinglet Optic Beam camp \u2014 and honestly the Noxgear Tracer2 is the other one I keep going back to for race nights. So for LumaLoop to even get on my radar, I need to know how it sits on the shoulders during a hard effort, what the lumen output and "
    },
    {
      "speaker": "Sage C.",
      "stance": "needs_more_information",
      "text": "Coming at this from a visibility standpoint, what I want to know about LumaLoop is the actual lumen output, beam pattern, and whether it's been tested for side/rear conspicuity \u2014 not just forward throw. My anchor for 'bright enough to be safe' is something like the Black Diamond "
    },
    {
      "speaker": "Maya A.",
      "stance": "needs_more_information",
      "text": "Format-wise, what I care about with something like LumaLoop is whether the carry is actually minimalist and comfortable \u2014 does it sit flat without bounce, and is there real storage for a phone, gel, and ID? I haven't seen specs on fluid volume options or strap construction yet, a"
    },
    {
      "speaker": "Skyler P.",
      "stance": "interested_if_proven",
      "text": "Honestly, I'm coming in skeptical until I see specifics. I already run with Nathan reflective gear \u2014 the HyperNight Stash Vest is $40 and has real reviews behind it, so LumaLoop needs to show me what it actually does better, at what price, with proof. Without lumens, runtime, bat"
    },
    {
      "speaker": "Skyler S.",
      "stance": "needs_more_information",
      "text": "Honestly, before I get excited about LumaLoop I need to know what it's actually going to cost. I've seen plenty of gear in adjacent categories where the build is solid and the idea is decent, but the sticker price is hard to justify unless it's replacing something I already rely "
    },
    {
      "speaker": "Xael L.",
      "stance": "needs_more_information",
      "text": "As someone who runs in low-light conditions, what I care about with something like LumaLoop is whether it actually solves the visibility problem better than what I already use \u2014 a decent headlamp with a strobe mode covers a lot of ground for me. I'd want to see specifics: lumen o"
    },
    {
      "speaker": "Jordan C.",
      "stance": "curious_but_unconvinced",
      "text": "Coming at this as someone who runs with a Tracer2 \u2014 that bar is high for me. The Tracer2 is featherlight, 360-degree visible, and the multicolor LEDs actually get noticed by drivers, so anything new in this space has to clear that. I'm open to hearing what LumaLoop does different"
    },
    {
      "speaker": "Quinn V.",
      "stance": "needs_more_information",
      "text": "For me, anything in this space lives or dies on visibility \u2014 how far off can a driver actually see it, and does it stay put when you're moving? I'd want to know the lumen output, beam pattern, and battery runtime before I'd compare it seriously to a clip-on chest light or a headl"
    },
    {
      "speaker": "Xael B.",
      "stance": "curious_but_unconvinced",
      "text": "Look, I run year-round in Minnesota and my Amphipod gear plus a Noxgear Tracer 2 has been rock solid through sub-zero winters \u2014 I can cinch it down and it doesn't bounce on race pace efforts. So before I get excited about LumaLoop, I want to know exactly how it attaches, how it h"
    }
  ],
  "main_arguments_raised": [
    {
      "speaker": "Jules J.",
      "argument": "Logan, I get wanting parity with the Tracer2 on LED count and fiber thickness, but for evening road running I care less about the spec sheet and more about whether drivers actually see the thing at 100+ yards in mixed light. Has anyone pushed for a side-by-side visibility compari"
    },
    {
      "speaker": "Logan C.",
      "argument": "Fair points on lumens and run-time, but I think we're letting the conversation drift toward 'flashlight' specs when LumaLoop seems pitched as a visibility/format play \u2014 which is a different category. My challenge: before anyone benchmarks it against a Black Diamond Sprinter or Fl"
    },
    {
      "speaker": "Kerry K.",
      "argument": "My challenge to the group: we're all listing spec wishlists \u2014 lumens, LEDs, fiber diameter, mounting \u2014 but nobody has pointed at a single independent test or a published spec sheet for LumaLoop. Before I'd even rank it against a Flare RT or Tracer2, I want third-party lumen measu"
    },
    {
      "speaker": "Jules M.",
      "argument": "Logan, fair on the LED and fiber specs, but for a convenience buyer like me that's not the bar that matters \u2014 I want to know weight on the torso, on/off glove-friendliness, charge time, and whether the battery lasts a full 2-hour run without a top-up. A Tracer2-style spec sheet d"
    },
    {
      "speaker": "Ellis G.",
      "argument": "Logan's spec list is a decent start, but it's missing what actually matters for endurance use: how does LumaLoop sit on a loaded waist pack or vest at hour four, and what's the documented run time at max output \u2014 not best-case lab numbers. I've had reflective and lit gear ride up"
    },
    {
      "speaker": "Marlowe B.",
      "argument": "Logan, I get wanting Tracer2-style spec parity \u2014 LED count, fiber diameter, dual-color \u2014 but for a running light those are inputs, not outcomes. What I'd push for instead is measured lumens at the beam, side-visibility angle in degrees, and grams on the shoulder over a 90-minute "
    },
    {
      "speaker": "Riley C.",
      "argument": "Casey, I hear you on the cost comparison, but for me the bigger question isn't just dollars \u2014 it's whether LumaLoop is actually one less thing to think about versus a vest plus a band plus charging two LEDs. If it doesn't clearly cut steps out of my routine, I'd rather stick with"
    },
    {
      "speaker": "Avery A.",
      "argument": "Casey, the $15 vest plus LED band comparison is the right floor, but it's not quite apples-to-apples until we see LumaLoop's actual reflective square inchage and lumen output side-by-side. My Nathan HyperNight vest is $40 and I still want to see an EN 17353 or ANSI 107 reference "
    },
    {
      "speaker": "Casey P.",
      "argument": "Avery, I hear you on wanting EN 17353 or ANSI 107 numbers, but specs alone don't answer the real question \u2014 what's the delta in actual driver-detection distance between LumaLoop and a $15 vest plus a $10 clip light? Lumens and reflective square inches look impressive on a sheet, "
    },
    {
      "speaker": "Gray T.",
      "argument": "Avery's right to push on specs, but I'd go further: I want to see LumaLoop's beam pattern and reflective performance side-by-side with something like the Black Diamond Sprinter's 275-lumen output and rear red blinker. 'Visibility' is meaningless without lux at distance, runtime a"
    },
    {
      "speaker": "Jordan N.",
      "argument": "Avery, I hear you on the spec sheet, but specs alone don't tell me what LumaLoop actually IS on my body or my pack \u2014 a 200-lumen output means something very different on a chest strap vs. a clip-on vs. a woven-in band. Before I care about EN 17353 numbers, I need the brand to cle"
    },
    {
      "speaker": "Nico K.",
      "argument": "Avery, I'm with you on wanting hard specs, but for my use case raw lumens and EN 17353 numbers don't tell me what I actually need to know \u2014 does a driver pulling out of a side street at 6am see me AND my dog from 100+ meters, and from the side, not just head-on? I'd want to see r"
    },
    {
      "speaker": "Casey C.",
      "argument": "Skyler's right to want certifications, but I'd push it further \u2014 show me a side-by-side at 100 yards with car headlights at the angles drivers actually approach from, not a studio shot. My Nathan vest plus a clip light gives me reflective return AND active emission; what's LumaLo"
    },
    {
      "speaker": "Gray P.",
      "argument": "Skyler, I hear you on wanting independent tests and certifications, but honestly that bar feels like it could keep me from ever trying anything new \u2014 by the time all that exists, half of us will have already moved on. My pushback is simpler: can you actually slip LumaLoop on over"
    },
    {
      "speaker": "Gray P.",
      "argument": "Skyler's right to demand independent tests, but I'd push further: I want sustained-lumen burn time at the actual setting I'd run with, not peak output for the first 30 seconds. Nico's Tracer 2 reference is fair \u2014 anyone pitching LumaLoop needs to show it holds calibrated brightne"
    },
    {
      "speaker": "Nico W.",
      "argument": "Skyler, I'm with you on wanting independent tests, but let's add a price column to that comparison sheet \u2014 visibility per dollar matters. My Tracer 2 hits 360-degree LED plus 3M reflective for under a hundred; if LumaLoop can't show me hard side-by-side proof AND land in that bal"
    },
    {
      "speaker": "Skyler K.",
      "argument": "Gray, I hear you on burn time and beam pattern, but I'd push further: without third-party photometric data and an independent drop/rain test, sustained-lumen claims from the brand itself are basically marketing. And to everyone leaning on personal favorites \u2014 Tracer 2, Nathan, cl"
    },
    {
      "speaker": "Yarrow M.",
      "argument": "Skyler's right that we need independent proof, but I want to push further: for those of us actually running, the test that matters isn't a static visibility chart \u2014 it's how LumaLoop performs at a 9-minute mile pace in rain, with bounce, over a 60-minute run. Has anyone seen foot"
    },
    {
      "speaker": "Tatum W.",
      "argument": "Sage D., I hear you on the Tracer2's bounce-free feel, but a fiber-optic harness and a head-mounted light like my Sprinter aren't really doing the same job \u2014 one's a torso 360 marker, the other's actually lighting the trail in front of you. Before we lump LumaLoop into either buc"
    },
    {
      "speaker": "Sage D.",
      "argument": "Logan, review averages are fine for sorting noise, but they won't tell you whether a harness actually stays put on a hard downhill or in a soaked shell \u2014 that's a fit-and-bounce question, not a star-rating question. What I want from LumaLoop specifically is a side-by-side bounce "
    }
  ],
  "main_objections_that_spread": [
    {
      "keyword": "lumens",
      "raised_in_turns": 82
    },
    {
      "keyword": "review",
      "raised_in_turns": 65
    },
    {
      "keyword": "proof",
      "raised_in_turns": 43
    },
    {
      "keyword": "durab",
      "raised_in_turns": 31
    },
    {
      "keyword": "weather",
      "raised_in_turns": 28
    },
    {
      "keyword": "ip rating",
      "raised_in_turns": 24
    },
    {
      "keyword": "battery life",
      "raised_in_turns": 18
    },
    {
      "keyword": "warrant",
      "raised_in_turns": 10
    },
    {
      "keyword": "cheaper",
      "raised_in_turns": 3
    }
  ],
  "arguments_that_changed_minds": [],
  "arguments_that_failed": [
    {
      "persona": "Riley C.",
      "held_at": "interested_if_proven",
      "reasoning": "I came in leaning convenience-first and a bit cautious, and the discussion nudged me from plain skepticism to open-but-needing-evidence. I haven't actually used the thing, so I'm relying on comparisons to alternatives I already know work for me, and nothing I heard was disqualify"
    },
    {
      "persona": "Avery A.",
      "held_at": "interested_if_proven",
      "reasoning": "I came in skeptical because I haven't handled the product and my benchmarks are things like the Nathan reflective vest at $40 and Reflex slap bands \u2014 proven gear at known prices. The discussion gave me reasons to keep an open mind, but nothing replaces seeing independent lumen/re"
    },
    {
      "persona": "Jordan N.",
      "held_at": "interested_if_proven",
      "reasoning": "I came in anchored to what I already trust for riding \u2014 cargo shorts with real pockets, quick-dry fabric, secure storage \u2014 so my bar for a new format is whether it actually solves a fit or function problem better than what I wear now. The discussion nudged me a little: I'm open t"
    },
    {
      "persona": "Maya C.",
      "held_at": "interested_if_proven",
      "reasoning": "Coming in I'm an Amphipod Xinglet wearer and the Tracer2 is my mental benchmark for high-vis vest-style gear, so a new entrant has a steep hill to climb with me. The discussion nudged me from straight skepticism to genuinely curious, but I haven't worn the thing \u2014 I need bounce/c"
    },
    {
      "persona": "Blair D.",
      "held_at": "interested_if_proven",
      "reasoning": "Coming at this as a runner who actually carries a handheld on course because aid stations don't always have electrolytes, I can see a real use case here, but I haven't tried this product so I'm not going to pretend I know how it performs. The discussion nudged me from neutral cur"
    },
    {
      "persona": "Winslow F.",
      "held_at": "curious_but_unconvinced",
      "reasoning": "My Tracer 2 has been rock solid through Minnesota winters at sub-zero, so the bar to switch is high and I haven't actually used this thing. The pitch is interesting enough that I'd watch it, but nothing I've heard tells me it beats what's already strapped to my chest on every dar"
    },
    {
      "persona": "Morgan A.",
      "held_at": "interested_if_proven",
      "reasoning": "Coming in I was leaning skeptical because I haven't actually used the product and I default to wanting hard evidence before I commit. The discussion gave me reasons to keep an open mind, but nothing I heard substitutes for independent proof \u2014 I'd still need durability data, safet"
    },
    {
      "persona": "Oakley W.",
      "held_at": "interested_if_proven",
      "reasoning": "My use case is concrete: night walks, alone, where I want at least 1000 lumens of reliable output. I came in skeptical because I haven't handled the unit and don't know its runtime, beam pattern, or durability versus what I'd compare it to like an Olight Warrior or a Fenix PD36R."
    },
    {
      "persona": "Lennon L.",
      "held_at": "interested_if_proven",
      "reasoning": "Coming in I cared most about fit and feel \u2014 the kind of thing where the right liner or underlining makes or breaks a vest over a long day. Without having actually worn this product, I can only compare it to packs I trust, and the format pitch is intriguing but unverified. Group c"
    },
    {
      "persona": "Sage W.",
      "held_at": "interested_if_proven",
      "reasoning": "Coming in I was curious but skeptical \u2014 for long unorganized trail runs, my gear has to just work, and I haven't actually put hands on this thing. The discussion nudged me a bit because the customization angle and the use-case fit for endurance training sounded plausible, but not"
    },
    {
      "persona": "Skyler P.",
      "held_at": "interested_if_proven",
      "reasoning": "I came in anchored to my Nathan setup \u2014 the HyperNight Stash Vest at $40 with documented reviews is a known quantity for me, and nothing I heard made me ready to switch sight unseen. That said, I'm willing to entertain it if there's hard proof: independent reflectivity testing, d"
    },
    {
      "persona": "Skyler S.",
      "held_at": "curious_but_unconvinced",
      "reasoning": "I came in skeptical on price and I'm leaving in roughly the same place \u2014 interested enough to keep an eye on it, but not sold without seeing what you actually get for the money versus simpler options I already trust. The discussion gave me some useful framing, but nothing concret"
    },
    {
      "persona": "Jordan C.",
      "held_at": "interested_if_proven",
      "reasoning": "I came in anchored to my Tracer2 \u2014 it's light, 360\u00b0 visible, and I know exactly how it performs on night runs. Through the discussion I heard enough about this new option to be curious, but nothing I can independently verify since I haven't worn it myself. I'd move further if I s"
    },
    {
      "persona": "Xael B.",
      "held_at": "interested_if_proven",
      "reasoning": "Coming in I lean hard on my Tracer 2 \u2014 it's been rock solid through Minnesota winters, sub-zero, doesn't bounce when cinched down. Nothing in this discussion gave me hands-on proof the new option beats that for cold-weather race use, but I'm not closed off if the specs and durabi"
    },
    {
      "persona": "Reese M.",
      "held_at": "interested_if_proven",
      "reasoning": "What pulled me in from the start was the quick-access gel slots \u2014 that's exactly the kind of mid-run convenience I look for, and it sounds better than fumbling with a waistband pocket on competitor packs. But I haven't actually run with it, so I'm not ready to commit; I'd want to"
    }
  ],
  "public_vs_private_opinion_change": {
    "pre_stance_distribution": {
      "interested_if_proven": 31,
      "skeptical": 7,
      "needs_more_information": 21,
      "curious_but_unconvinced": 7
    },
    "final_stance_distribution": {
      "interested_if_proven": 54,
      "skeptical": 4,
      "curious_but_unconvinced": 7,
      "needs_more_information": 1
    },
    "delta_classification": {
      "resistance": 15,
      "no_change": 51
    }
  },
  "social_influence_analysis": {
    "delta_classification": {
      "resistance": 15,
      "no_change": 51
    },
    "overcooperation_audit": {
      "converged": false,
      "public_majority_stance": "needs_more_information",
      "public_majority_pct": 0.388,
      "final_majority_stance": "interested_if_proven",
      "final_majority_pct": 0.818,
      "private_dissent_present": true,
      "flag": false,
      "warning": null
    }
  },
  "persona_cluster_differences": {
    "interested_if_proven": [
      "Riley C.",
      "Avery A.",
      "Jordan N.",
      "Nico K.",
      "Tatum W.",
      "Sage D.",
      "Logan J.",
      "Maya C.",
      "Sage C.",
      "Maya A.",
      "Jules J.",
      "Logan C.",
      "Kerry K.",
      "Jules M.",
      "Ellis G.",
      "Marlowe B.",
      "Wren A.",
      "Blair D.",
      "Logan R.",
      "Morgan A.",
      "Lennon J.",
      "Umber M.",
      "Vesper F.",
      "Drew L.",
      "Drew W.",
      "Vesper G.",
      "Ellis L.",
      "Quinn T.",
      "Quinn L.",
      "Oakley W.",
      "Jules R.",
      "Nico W.",
      "Skyler N.",
      "Nico W.",
      "Casey K.",
      "Morgan F.",
      "Morgan T.",
      "Lennon L.",
      "Drew J.",
      "Sage W.",
      "Skyler T.",
      "Skyler P.",
      "Xael L.",
      "Jordan C.",
      "Xael B.",
      "Casey C.",
      "Gray P.",
      "Gray P.",
      "Skyler K.",
      "Yarrow M.",
      "Riley V.",
      "Reese M.",
      "Yarrow R.",
      "Finley C."
    ],
    "skeptical": [
      "Casey P.",
      "Sage G.",
      "Riley F.",
      "Phoenix K."
    ],
    "curious_but_unconvinced": [
      "Gray T.",
      "Winslow F.",
      "Marlowe F.",
      "Maya B.",
      "Skyler S.",
      "Nico W.",
      "Xael K."
    ],
    "needs_more_information": [
      "Quinn V."
    ]
  },
  "proof_demands": [
    {
      "speaker": "Quinn L.",
      "proof_need": "Independent durability + visibility test data at sub-zero temps with battery life numbers"
    },
    {
      "speaker": "Marlowe F.",
      "proof_need": "MSRP plus a side-by-side runtime/lumens/weight comparison against established competitors"
    },
    {
      "speaker": "Riley C.",
      "proof_need": "A short real-world demo showing the everyday use case and setup time."
    },
    {
      "speaker": "Avery A.",
      "proof_need": "Independent visibility test (distance in meters, lumens, runtime) plus MSRP"
    },
    {
      "speaker": "Casey P.",
      "proof_need": "Transparent price and a side-by-side cost-per-lumen-hour vs Noxgear/Nathan."
    },
    {
      "speaker": "Gray T.",
      "proof_need": "Independent side-by-side field test: lumens, runtime at high, weight on head, and bounce on a 10k night run."
    },
    {
      "speaker": "Jordan N.",
      "proof_need": "A clear spec sheet: physical form, dimensions, materials, and how it integrates with existing kit."
    },
    {
      "speaker": "Nico K.",
      "proof_need": "Side-by-side visibility distance test (meters seen by a driver) vs. a standard LED collar, plus battery runtime and weather resistance specs."
    },
    {
      "speaker": "Tatum W.",
      "proof_need": "Side-by-side spec sheet: lumens, runtime, weight, IP rating, and price vs Sprinter."
    },
    {
      "speaker": "Sage D.",
      "proof_need": "Side-by-side run footage and weight/battery specs vs. Noxgear Tracer2, ideally with a return window."
    },
    {
      "speaker": "Logan J.",
      "proof_need": "Independent reflectivity/visibility test results (e.g., ANSI/ISO retroreflective rating) plus a meaningful sample of verified user reviews."
    },
    {
      "speaker": "Maya C.",
      "proof_need": "Independent side-by-side: weight, bounce, runtime vs Xinglet and Tracer2"
    },
    {
      "speaker": "Sage C.",
      "proof_need": "Independent lumen/runtime specs and a side-by-side visibility test against a known benchmark like the BD Sprinter."
    },
    {
      "speaker": "Maya A.",
      "proof_need": "Spec sheet with weight, fluid volume, and storage pockets, plus side-by-side photos against an established carrier."
    },
    {
      "speaker": "Jules J.",
      "proof_need": "Clear IPX rating plus runtime/lumens vs Nathan or Knuckle Lights"
    },
    {
      "speaker": "Logan C.",
      "proof_need": "A detailed spec sheet plus side-by-side night visibility footage vs. Tracer360."
    },
    {
      "speaker": "Kerry K.",
      "proof_need": "Independent daytime visibility/runtime test vs. a known benchmark like the Flare RT."
    },
    {
      "speaker": "Jules M.",
      "proof_need": "Published weight, lumen/runtime curve, and a side-by-side against a Sprinter-class headlamp."
    },
    {
      "speaker": "Ellis G.",
      "proof_need": "Detailed spec sheet plus independent long-run reviews (bounce, chafe, capacity, gel/chew access)"
    },
    {
      "speaker": "Marlowe B.",
      "proof_need": "Independently measured lumens, runtime curve, and weight vs. a named competitor."
    },
    {
      "speaker": "Wren A.",
      "proof_need": "Published MSRP plus lumens, runtime, and weight in a spec sheet"
    },
    {
      "speaker": "Blair D.",
      "proof_need": "A concrete use-case demo or spec sheet showing how it performs in a real run scenario."
    },
    {
      "speaker": "Winslow F.",
      "proof_need": "Independent cold-weather/runtime testing and a side-by-side visibility comparison vs. Noxgear Tracer 2"
    },
    {
      "speaker": "Logan R.",
      "proof_need": "Independent test results: measured lumens, runtime per charge, IPX rating, and weight on-body."
    },
    {
      "speaker": "Morgan A.",
      "proof_need": "Third-party safety/durability testing plus detailed materials and care specs."
    },
    {
      "speaker": "Lennon J.",
      "proof_need": "Spec sheet + a real night-run visibility comparison vs Noxgear Tracer 2"
    },
    {
      "speaker": "Umber M.",
      "proof_need": "Side-by-side low-light visibility footage vs Nathan blinkers at realistic driver distances"
    },
    {
      "speaker": "Vesper F.",
      "proof_need": "A close-up demo or teardown showing assembly, materials, and tolerances \u2014 plus a clear return policy."
    },
    {
      "speaker": "Drew L.",
      "proof_need": "Independent run-test data: lumens, runtime, weight, and bounce vs FlipBelt"
    },
    {
      "speaker": "Drew W.",
      "proof_need": "Side-by-side fit/stability demo at running pace vs. Tracer2"
    }
  ],
  "positioning_implications": [
    "A subset of personas would shift positively given the right proof material \u2014 focus marketing claims on what they asked for.",
    "15 persona(s) actively resisted peer pressure \u2014 their dissenting reasoning is the contrarian signal worth validating with real users."
  ],
  "what_founder_should_test_next": [
    "Proof artifacts personas demanded most: lumens (x25), battery (x12), review (x5), durability (x4), ip rating (x2). Build small concept tests around each before scaling spend.",
    "Talk to real prospects matching the resisting personas' profile \u2014 their objection pattern is the contrarian risk.",
    "Validate this synthetic discussion against a small real-people discussion before treating any signal as load-bearing."
  ],
  "caveats": [
    "This is a synthetic discussion simulation, not a real focus group.",
    "n=30 persisted society; 5 groups of 6.",
    "Not representative of the California market.",
    "Not a demand forecast.",
    "Not a launch verdict.",
    "Personas are run-scoped and brief-scoped. No global personas.",
    "Product 'LumaLoop' is unlaunched; no persona has actually used it.",
    "Psychology trait values are simulation controls, not real psychological diagnoses."
  ],
  "appendix": {
    "discussion_turn_count": 264,
    "pre_ballot_count": 66,
    "reflection_ballot_count": 61,
    "final_ballot_count": 66,
    "memory_atom_count": 528,
    "memory_atoms_by_type": {
      "psychology": 264,
      "trait": 132,
      "evidence": 132
    },
    "forbidden_claim_audit": {
      "scanner_version": "9A.4.universal",
      "fake_target_product_use_count": 0,
      "forecast_or_verdict_count": 0,
      "any_fake_target_product_use": false,
      "any_forecast_or_verdict": false,
      "fake_use_findings": [],
      "forecast_findings": []
    },
    "sensitive_inference_audit": {
      "scanner_version": "9A.4.universal",
      "finding_count": 0,
      "any_sensitive_inference": false,
      "findings": []
    },
    "discussion_quality_scores": {
      "grounding_score": 1.0,
      "interaction_score": 1.0,
      "disagreement_score": 1.0,
      "non_overcooperation_score": 1.0,
      "memory_integrity_score": 1.0,
      "private_public_distinction_score": 1.0,
      "social_influence_score": 0.727,
      "stance_validity_score": 1.0,
      "anti_forecast_score": 1.0,
      "unlaunched_product_integrity_score": 1.0,
      "profile_usage_score": 1.0,
      "caveat_integrity_score": 1.0,
      "aggregate_score": 0.976,
      "ready_state": "READY_FOR_PROMPT_FIX",
      "rationale": [
        "aggregate=0.978 (anti_forecast=1.0, unlaunched=1.0, memory=1.0, private_public=1.0, interaction=1.0, profile_usage=1.0, non_overcooperation=1.0, stance_validity=1.0)",
        "scale_reliability=0.975 reflection_completeness=0.924 cost_efficiency=1.0 persisted_personas=66/66 calls=5/462 transient_retries=0 failed_calls=0 est_cost=$0.09/cap=$20.00"
      ],
      "scale_reliability_score": 0.975,
      "reflection_completeness_score": 0.924,
      "cost_efficiency_score": 1.0
    }
  }
}